daffalib/__init__.py
daffalib/api.py
daffalib/cli.py
daffalib-0.2.5.dist-info/licenses/LICENSE
daffalib-0.2.5.dist-info/METADATA
daffalib-0.2.5.dist-info/WHEEL
daffalib-0.2.5.dist-info/entry_points.txt
daffalib-0.2.5.dist-info/top_level.txt
daffalib-0.2.5.dist-info/RECORD
