Metadata-Version: 2.4
Name: daffalib
Version: 0.2.5
Summary: A modern and ultra-simple Python wrapper for the requests library, designed to simplify REST API interactions with flexible configuration and REPL support.
Author-email: Daffa Aditya Pratama <daffaaditya@daffadev.my.id>
License-Expression: MIT
Project-URL: Homepage, https://github.com/daffa-aditya-p/daffalib
Project-URL: Bug Tracker, https://github.com/daffa-aditya-p/daffalib/issues
Classifier: Programming Language :: Python :: 3
Classifier: Operating System :: OS Independent
Classifier: Intended Audience :: Developers
Classifier: Topic :: Software Development :: Libraries :: Python Modules
Classifier: Topic :: Internet :: WWW/HTTP
Requires-Python: >=3.8
License-File: LICENSE
Requires-Dist: requests>=2.31.0
Dynamic: license-file
